README.md
setup.py
sqlhttpcss/__init__.py
sqlhttpcss/shared_variable_client.py
sqlhttpcss.egg-info/PKG-INFO
sqlhttpcss.egg-info/SOURCES.txt
sqlhttpcss.egg-info/dependency_links.txt
sqlhttpcss.egg-info/requires.txt
sqlhttpcss.egg-info/top_level.txt