Metadata-Version: 2.1
Name: sqlhttpcss
Version: 0.5
Summary: これは、C#のアプリケーションとHTTP通信して、データベース化したものです
Home-page: https://github.com/yourusername/my_library
Author: Your Name
Author-email: your.email@example.com
License: MIT
Platform: UNKNOWN
Classifier: Programming Language :: Python :: 3
Classifier: License :: OSI Approved :: MIT License
Classifier: Operating System :: OS Independent
Requires-Python: >=3.6
